MANIFEST.in
generator
settings.py
setup.cfg
setup.py
environment/gitlab-docs.sh
generated/LICENSE
generated/README
generated/pypi.tmp
generated/settings.tmp
generated/setup.cfg
generated/setup.py
generated/template.tmp
generated/data/__init__.py
gitlab-docs/generate.rb
gitlab-docs/index.html
gitlab-docs/sample.html
gitlab-docs/stylesheets/pygment_trac.css
gitlab-docs/stylesheets/styles.css
gl_api_generator.egg-info/PKG-INFO
gl_api_generator.egg-info/SOURCES.txt
gl_api_generator.egg-info/dependency_links.txt
gl_api_generator.egg-info/requires.txt
gl_api_generator.egg-info/top_level.txt
utils/__init__.py
utils/code.py
utils/download.py
utils/parse.py
utils/repository.py