Metadata-Version: 1.0
Name: gl-api-generator
Version: 1.5.0
Summary: A project for Convert Gitlab Documentation to Python Wrapper
Home-page: https://github.com/SmartDeveloperHub/gitlab-api-generator
Author: Alejandro F. Carrera
Author-email: alejandro.fernandez.carrera@centeropenmiddleware.com
License: Apache 2
Keywords: inner-source enhancer gitlab wrapper
Platform: UNKNOWN
